prohub/__init__.py
prohub/module1.py
prohub-0.1.dist-info/LICENSE
prohub-0.1.dist-info/METADATA
prohub-0.1.dist-info/WHEEL
prohub-0.1.dist-info/top_level.txt
prohub-0.1.dist-info/RECORD
